cocoa_time/__init__.py
cocoa_time-1.0.10.dist-info/LICENSE
cocoa_time-1.0.10.dist-info/METADATA
cocoa_time-1.0.10.dist-info/WHEEL
cocoa_time-1.0.10.dist-info/top_level.txt
cocoa_time-1.0.10.dist-info/RECORD
