Metadata-Version: 2.1
Name: cocoa_time
Version: 1.0.10
Summary: A cocoa core data timestamp library
Author: Edanick
Requires-Python: >=3.0
License-File: LICENSE
